{
  "homepage": "https://github.com/bazel-contrib/tar.bzl",
  "maintainers": [
    {
      "email": "alex@aspect.build",
      "github": "alexeagle",
      "name": "Alex Eagle"
    },
    {
      "email": "sahin@aspect.build",
      "github": "thesayyn",
      "name": "Şahin Yort"
    },
    {
      "email": "dzbarsky@gmail.com",
      "github": "dzbarsky",
      "name": "David Zbarsky"
    },
    {
      "email": "jason@aspect.build",
      "github": "jbedard",
      "name": "Jason Bedard"
    }
  ],
  "repository": ["github:bazel-contrib/tar.bzl"],
  "versions": [],
  "yanked_versions": {}
}
